{"cameraMode":{"drawMode":0,"name":"Shaded","section":"Shading Mode"},"sceneLighting":true,"audioPlay":false,"sceneViewState":{"m_AlwaysRefresh":false,"showFog":true,"showSkybox":true,"showFlares":true,"showImageEffects":true,"showParticleSystems":true,"showVisualEffectGraphs":true,"m_FxEnabled":true},"in2DMode":false,"pivot":{"x":1.529625415802002,"y":6.44968318939209,"z":-14.958937644958496},"rotation":{"x":-0.206559419631958,"y":0.20804806053638459,"z":-0.044998038560152057,"w":-0.9550074338912964},"size":1.6633332967758179,"orthographic":false}